odoo/addons/product_abc_classification_sale_stock/README.rst
odoo/addons/product_abc_classification_sale_stock/__init__.py
odoo/addons/product_abc_classification_sale_stock/__manifest__.py
odoo/addons/product_abc_classification_sale_stock/demo/abc_classification_level.xml
odoo/addons/product_abc_classification_sale_stock/demo/abc_classification_profile.xml
odoo/addons/product_abc_classification_sale_stock/i18n/es.po
odoo/addons/product_abc_classification_sale_stock/i18n/fr.po
odoo/addons/product_abc_classification_sale_stock/i18n/it.po
odoo/addons/product_abc_classification_sale_stock/i18n/product_abc_classification_sale_stock.pot
odoo/addons/product_abc_classification_sale_stock/models/__init__.py
odoo/addons/product_abc_classification_sale_stock/models/abc_classification_product_level.py
odoo/addons/product_abc_classification_sale_stock/models/abc_classification_profile.py
odoo/addons/product_abc_classification_sale_stock/models/abc_sale_stock_level_history.py
odoo/addons/product_abc_classification_sale_stock/readme/CONTRIBUTORS.rst
odoo/addons/product_abc_classification_sale_stock/readme/DESCRIPTION.rst
odoo/addons/product_abc_classification_sale_stock/readme/USAGE.rst
odoo/addons/product_abc_classification_sale_stock/security/abc_sale_stock_level_history.xml
odoo/addons/product_abc_classification_sale_stock/static/description/icon.png
odoo/addons/product_abc_classification_sale_stock/static/description/index.html
odoo/addons/product_abc_classification_sale_stock/tests/__init__.py
odoo/addons/product_abc_classification_sale_stock/tests/test_abc_classification_profile.py
odoo/addons/product_abc_classification_sale_stock/views/abc_classification_product_level.xml
odoo/addons/product_abc_classification_sale_stock/views/abc_classification_profile.xml
odoo/addons/product_abc_classification_sale_stock/views/abc_sale_stock_level_history.xml
odoo_addon_product_abc_classification_sale_stock-16.0.1.0.2.dist-info/METADATA
odoo_addon_product_abc_classification_sale_stock-16.0.1.0.2.dist-info/WHEEL
odoo_addon_product_abc_classification_sale_stock-16.0.1.0.2.dist-info/top_level.txt
odoo_addon_product_abc_classification_sale_stock-16.0.1.0.2.dist-info/RECORD
