Metadata-Version: 2.1
Name: odoo-addon-product_abc_classification_sale_stock
Version: 16.0.1.0.2
Summary: Compute ABC classification from the number of delivered sale order line by product
Home-page: https://github.com/OCA/product-attribute
Author: ACSONE SA/NV,Odoo Community Association (OCA)
Author-email: support@odoo-community.org
License: AGPL-3
Classifier: Programming Language :: Python
Classifier: Framework :: Odoo
Classifier: Framework :: Odoo :: 16.0
Classifier: License :: OSI Approved :: GNU Affero General Public License v3
Requires-Python: >=3.10
Requires-Dist: freezegun
Requires-Dist: odoo-addon-product-abc-classification <16.1dev,>=16.0dev
Requires-Dist: odoo <16.1dev,>=16.0a
